lc3vm.py
lc3vm-1.1.dist-info/entry_points.txt
lc3vm-1.1.dist-info/WHEEL
lc3vm-1.1.dist-info/METADATA
lc3vm-1.1.dist-info/RECORD
